[
	{	
		"reportNo":"168465165",
		"patientName":"jsk",
		"patientAge":"55岁",
		"reportType":"静态心电报告",
		"createTime":"2018-11-25",
		"reportId":"684168465146851648612652652"
	},
	{	
		"reportNo":"168465165",
		"patientName":"jsk",
		"patientAge":"55岁",
		"reportType":"静态心电报告",
		"createTime":"2018-11-25",
		"reportId":"684168465146851648612652652"
	},
	{	
		"reportNo":"168465165",
		"patientName":"jsk",
		"patientAge":"55岁",
		"reportType":"静态心电报告",
		"createTime":"2018-11-25",
		"reportId":"684168465146851648612652652"
	},
	{	
		"reportNo":"168465165",
		"patientName":"jsk",
		"patientAge":"55岁",
		"reportType":"静态心电报告",
		"createTime":"2018-11-25",
		"reportId":"684168465146851648612652652"
	}

]
